hilbert_bytes/__init__.py
hilbert_bytes/_hilbert.py
hilbert_bytes/py.typed
hilbert_bytes-0.6.0.dist-info/METADATA
hilbert_bytes-0.6.0.dist-info/WHEEL
hilbert_bytes-0.6.0.dist-info/licenses/LICENSE
hilbert_bytes-0.6.0.dist-info/RECORD
