Metadata-Version: 2.4
Name: hilbert-bytes
Version: 0.6.0
Summary: A python library for converting between d-dimensional points and indices on a hilbert curve
License-File: LICENSE
Requires-Python: >=3.12
Requires-Dist: numba>=0.61.0
Requires-Dist: numpy>=2.1.3
